LICENCE.txt
README.md
setup.py
hashboard/__init__.py
hashboard/history.py
hashboard/parsing.py
hashboard/rollouts.py
hashboard/simulator.py
hashboard/timeline.py
hashboard.egg-info/PKG-INFO
hashboard.egg-info/SOURCES.txt
hashboard.egg-info/dependency_links.txt
hashboard.egg-info/not-zip-safe
hashboard.egg-info/requires.txt
hashboard.egg-info/top_level.txt