Metadata-Version: 2.1
Name: hashboard
Version: 0.1.4
Summary: Tool for estimating the profitability of bitcoin ASICs
Home-page: https://gitlab.com/apgoucher/hashboard
Author: Adam P. Goucher
Author-email: adam@hatsya.com
License: MIT
Platform: UNKNOWN
Classifier: Development Status :: 2 - Pre-Alpha
Classifier: License :: OSI Approved :: MIT License
Classifier: Programming Language :: Python :: 3.8
Classifier: Intended Audience :: Science/Research
Classifier: Topic :: Scientific/Engineering :: Mathematics
